ggguan_2025miao/__init__.py
ggguan_2025miao/ggguan_2025.py
ggguan_2025miao-1.0.0.dist-info/LICENSE
ggguan_2025miao-1.0.0.dist-info/METADATA
ggguan_2025miao-1.0.0.dist-info/WHEEL
ggguan_2025miao-1.0.0.dist-info/entry_points.txt
ggguan_2025miao-1.0.0.dist-info/top_level.txt
ggguan_2025miao-1.0.0.dist-info/RECORD
