Metadata-Version: 2.1
Name: ggguan_2025miao
Version: 1.0.0
Summary: miaomiaomiao.
Home-page: https://github.com/ggguan0314/ggguan_2025miao
Author: Emoli
Author-email: 2586132625@qq.com
Classifier: Programming Language :: Python :: 3
Classifier: License :: OSI Approved :: MIT License
Classifier: Operating System :: OS Independent
Requires-Python: >=3.6
License-File: LICENSE
Requires-Dist: matplotlib>=3.0
Requires-Dist: numpy>=1.0
